scopus_scraping/__init__.py
scopus_scraping/errors.py
scopus_scraping/logger.py
scopus_scraping/utils.py
scopus_scraping/models/__init__.py
scopus_scraping/models/records.py
scopus_scraping/models/scopus_citations_url.py
scopus_scraping/models/scrape_result.py
scopus_scraping/tools/__init__.py
scopus_scraping/tools/base.py
scopus_scraping/tools/selenium/__init__.py
scopus_scraping/tools/selenium/models.py
scopus_scraping/tools/selenium/tool.py
scopus_scraping-0.1.0.dist-info/METADATA
scopus_scraping-0.1.0.dist-info/WHEEL
scopus_scraping-0.1.0.dist-info/entry_points.txt
scopus_scraping-0.1.0.dist-info/licenses/LICENSE
scopus_scraping-0.1.0.dist-info/RECORD
