Metadata-Version: 2.4
Name: scopus-scraping
Version: 0.1.0
Summary: Add your description here
Author-email: Anatoliy Lazovyj <Lazoviy3000@ya.ru>
License-File: LICENSE
Requires-Python: >=3.13
Requires-Dist: loguru>=0.7.3
Requires-Dist: pydantic>=2.11.7
Requires-Dist: selenium>=4.33.0
Requires-Dist: setuptools>=80.9.0
Requires-Dist: undetected-chromedriver>=3.5.5
Requires-Dist: webdriver-manager>=4.0.2
